.gitignore
CHANGES.rst
COPYRIGHT.txt
LICENSE.txt
README.rst
buildout.cfg
livetest.py
setup.cfg
setup.py
repoze/__init__.py
repoze.pgtextindex.egg-info/PKG-INFO
repoze.pgtextindex.egg-info/SOURCES.txt
repoze.pgtextindex.egg-info/dependency_links.txt
repoze.pgtextindex.egg-info/entry_points.txt
repoze.pgtextindex.egg-info/namespace_packages.txt
repoze.pgtextindex.egg-info/not-zip-safe
repoze.pgtextindex.egg-info/requires.txt
repoze.pgtextindex.egg-info/top_level.txt
repoze/pgtextindex/__init__.py
repoze/pgtextindex/db.py
repoze/pgtextindex/index.py
repoze/pgtextindex/interfaces.py
repoze/pgtextindex/queryconvert.py
repoze/pgtextindex/queryparser.py
repoze/pgtextindex/tests/__init__.py
repoze/pgtextindex/tests/test_db.py
repoze/pgtextindex/tests/test_index.py
repoze/pgtextindex/tests/test_queryconvert.py
repoze/pgtextindex/tests/test_queryparser.py