Metadata-Version: 1.1
Name: repoze.pgtextindex
Version: 1.3
Summary: Text index for repoze.catalog based on PostgreSQL 8.4+
Home-page: http://pypi.python.org/pypi/repoze.pgtextindex
Author: Shane Hathaway
Author-email: shane@hathawaymix.org
License: BSD-derived (http://www.repoze.org/LICENSE.txt)
Keywords: repoze catalog ZODB PostgreSQL text index
Platform: UNKNOWN
Classifier: Development Status :: 5 - Production/Stable
Classifier: Intended Audience :: Developers
Classifier: Programming Language :: Python
Classifier: Framework :: ZODB
Classifier: License :: Repoze Public License
Classifier: Topic :: Database
